_orbits.cpython-39-darwin.so
fastAK.cpython-39-darwin.so
fastGB.cpython-39-darwin.so
pyimrphenomD.cpython-39-darwin.so
ldc/common/constants/__init__.py
ldc/common/constants/cosmology.py
ldc/common/constants/lisaconstants.hpp
ldc/common/constants/nature.py
ldc/common/constants/supported.py
ldc/common/constants/pdb/PdbParam.py
ldc/common/series/__init__.py
ldc/common/series/tdi.py
ldc/common/series/timeseries.py
ldc/common/tools/__init__.py
ldc/common/tools/smoothing.py
ldc/common/tools/snr.py
ldc/common/tools/spa.py
ldc/common/tools/spherical_harmonic.py
ldc/common/tools/trigo.py
ldc/common/tools/windows.py
ldc/io/hdf5/__init__.py
ldc/io/hdf5/hdf5.py
ldc/io/npz/__init__.py
ldc/io/npz/npz.py
ldc/io/test/demo.py
ldc/io/txt/__init__.py
ldc/io/txt/txt.py
ldc/io/yml/__init__.py
ldc/io/yml/yml.py
ldc/lisa/noise/__init__.py
ldc/lisa/noise/noise.py
ldc/lisa/noise/test/demo.py
ldc/lisa/orbits/__init__.py
ldc/lisa/orbits/orbits.py
ldc/lisa/orbits/lib/c_wrapper.cc
ldc/lisa/orbits/lib/c_wrapper.h
ldc/lisa/orbits/lib/common.cc
ldc/lisa/orbits/lib/common.hpp
ldc/lisa/orbits/lib/orbits.cc
ldc/lisa/orbits/lib/orbits.hpp
ldc/lisa/orbits/lib/pyorbits.pyx
ldc/lisa/orbits/test/demo.py
ldc/lisa/orbits/test/graph.py
ldc/lisa/orbits/test/run_lisacode.py
ldc/lisa/orbits/test/run_lisanode.py
ldc/lisa/orbits/test/run_lisaorbits.py
ldc/lisa/projection/__init__.py
ldc/lisa/projection/projectedstrain.py
ldc/lisa/projection/test/demo.py
ldc/lisa/projection/test/numeric.py
ldc/utils/logging/__init__.py
ldc/waveform/fastAK/EMRItemplate.cc
ldc/waveform/fastAK/EMRItemplate.h
ldc/waveform/fastAK/FreqAK_RAv2.cc
ldc/waveform/fastAK/FreqAK_RAv2.h
ldc/waveform/fastAK/__init__.py
ldc/waveform/fastAK/fastAK.pyx
ldc/waveform/fastAK/test/demo.py
ldc/waveform/fastGB/GB.cc
ldc/waveform/fastGB/GB.h
ldc/waveform/fastGB/LISA.cc
ldc/waveform/fastGB/LISA.h
ldc/waveform/fastGB/__init__.py
ldc/waveform/fastGB/pyGB.pyx
ldc/waveform/fastGB/test/demo.py
ldc/waveform/fastGB/test/perf.py
ldc/waveform/fastGB/test/stack.py
lisa_data_challenge-1.2.0.dist-info/LICENSE
lisa_data_challenge-1.2.0.dist-info/METADATA
lisa_data_challenge-1.2.0.dist-info/WHEEL
lisa_data_challenge-1.2.0.dist-info/top_level.txt
lisa_data_challenge-1.2.0.dist-info/RECORD
