Metadata-Version: 2.1
Name: lisa-data-challenge
Version: 1.2.0
Summary: LISA Data Challenge software
Home-page: https://lisa.pages.in2p3.fr/LDC
Author: ldc-dev
Author-email: ldc-dev@lisamission.org
License: MIT License
Project-URL: homepage, https://lisa-ldc.lal.in2p3.fr
Project-URL: documentation, https://lisa.pages.in2p3.fr/LDC
Requires-Python: >=3.7
License-File: LICENSE
Requires-Dist: numpy
Requires-Dist: scipy
Requires-Dist: astropy
Requires-Dist: xarray
Requires-Dist: h5py
Requires-Dist: matplotlib
Requires-Dist: lisaconstants
Requires-Dist: lisaorbits
